labs/__init__.py
labs/magic.py
joyful_labs-0.0.1.dist-info/METADATA
joyful_labs-0.0.1.dist-info/WHEEL
joyful_labs-0.0.1.dist-info/RECORD
